<?xml version="1.0" encoding="UTF-8"?>
<!DOCTYPE mapper PUBLIC "-//mybatis.org//DTD Mapper 3.0//EN" "http://mybatis.org/dtd/mybatis-3-mapper.dtd">
<mapper namespace="com.pugutang.spring.boot.dao.oldDao.OrderDoMapper">
  <resultMap id="BaseResultMap" type="com.pugutang.spring.boot.entity.OrderDo">
    <id column="order_id" jdbcType="INTEGER" property="order_id" />
    <result column="order_sn" jdbcType="VARCHAR" property="order_sn" />
    <result column="parent_sn" jdbcType="VARCHAR" property="parent_sn" />
    <result column="user_id" jdbcType="INTEGER" property="user_id" />
    <result column="order_status" jdbcType="BIT" property="order_status" />
    <result column="shop_id" jdbcType="INTEGER" property="shop_id" />
    <result column="site_id" jdbcType="INTEGER" property="site_id" />
    <result column="store_id" jdbcType="INTEGER" property="store_id" />
    <result column="pickup_id" jdbcType="INTEGER" property="pickup_id" />
    <result column="shipping_status" jdbcType="BIT" property="shipping_status" />
    <result column="pay_status" jdbcType="BIT" property="pay_status" />
    <result column="consignee" jdbcType="VARCHAR" property="consignee" />
    <result column="region_code" jdbcType="VARCHAR" property="region_code" />
    <result column="region_name" jdbcType="VARCHAR" property="region_name" />
    <result column="address" jdbcType="VARCHAR" property="address" />
    <result column="address_lng" jdbcType="VARCHAR" property="address_lng" />
    <result column="address_lat" jdbcType="VARCHAR" property="address_lat" />
    <result column="receiving_mode" jdbcType="BIT" property="receiving_mode" />
    <result column="tel" jdbcType="VARCHAR" property="tel" />
    <result column="email" jdbcType="VARCHAR" property="email" />
    <result column="postscript" jdbcType="VARCHAR" property="postscript" />
    <result column="best_time" jdbcType="VARCHAR" property="best_time" />
    <result column="pay_id" jdbcType="INTEGER" property="pay_id" />
    <result column="pay_code" jdbcType="VARCHAR" property="pay_code" />
    <result column="pay_name" jdbcType="VARCHAR" property="pay_name" />
    <result column="pay_sn" jdbcType="VARCHAR" property="pay_sn" />
    <result column="is_cod" jdbcType="BIT" property="is_cod" />
    <result column="order_amount" jdbcType="DECIMAL" property="order_amount" />
    <result column="order_points" jdbcType="INTEGER" property="order_points" />
    <result column="money_paid" jdbcType="DECIMAL" property="money_paid" />
    <result column="goods_amount" jdbcType="DECIMAL" property="goods_amount" />
    <result column="inv_fee" jdbcType="DECIMAL" property="inv_fee" />
    <result column="shipping_fee" jdbcType="DECIMAL" property="shipping_fee" />
    <result column="cash_more" jdbcType="DECIMAL" property="cash_more" />
    <result column="discount_fee" jdbcType="DECIMAL" property="discount_fee" />
    <result column="change_amount" jdbcType="DECIMAL" property="change_amount" />
    <result column="shipping_change" jdbcType="DECIMAL" property="shipping_change" />
    <result column="surplus" jdbcType="DECIMAL" property="surplus" />
    <result column="user_surplus" jdbcType="DECIMAL" property="user_surplus" />
    <result column="user_surplus_limit" jdbcType="DECIMAL" property="user_surplus_limit" />
    <result column="bonus_id" jdbcType="INTEGER" property="bonus_id" />
    <result column="shop_bonus_id" jdbcType="INTEGER" property="shop_bonus_id" />
    <result column="bonus" jdbcType="DECIMAL" property="bonus" />
    <result column="shop_bonus" jdbcType="DECIMAL" property="shop_bonus" />
    <result column="store_card_id" jdbcType="INTEGER" property="store_card_id" />
    <result column="store_card_price" jdbcType="DECIMAL" property="store_card_price" />
    <result column="integral" jdbcType="INTEGER" property="integral" />
    <result column="integral_money" jdbcType="DECIMAL" property="integral_money" />
    <result column="give_integral" jdbcType="INTEGER" property="give_integral" />
    <result column="order_from" jdbcType="VARCHAR" property="order_from" />
    <result column="add_time" jdbcType="INTEGER" property="add_time" />
    <result column="pay_time" jdbcType="INTEGER" property="pay_time" />
    <result column="shipping_time" jdbcType="INTEGER" property="shipping_time" />
    <result column="confirm_time" jdbcType="INTEGER" property="confirm_time" />
    <result column="delay_days" jdbcType="BIT" property="delay_days" />
    <result column="order_type" jdbcType="BIT" property="order_type" />
    <result column="service_mark" jdbcType="BIT" property="service_mark" />
    <result column="send_mark" jdbcType="BIT" property="send_mark" />
    <result column="shipping_mark" jdbcType="BIT" property="shipping_mark" />
    <result column="buyer_type" jdbcType="BIT" property="buyer_type" />
    <result column="evaluate_status" jdbcType="BIT" property="evaluate_status" />
    <result column="evaluate_time" jdbcType="INTEGER" property="evaluate_time" />
    <result column="end_time" jdbcType="INTEGER" property="end_time" />
    <result column="is_distrib" jdbcType="BIT" property="is_distrib" />
    <result column="distrib_status" jdbcType="BIT" property="distrib_status" />
    <result column="is_show" jdbcType="VARCHAR" property="is_show" />
    <result column="is_delete" jdbcType="BIT" property="is_delete" />
    <result column="close_reason" jdbcType="VARCHAR" property="close_reason" />
    <result column="cash_user_id" jdbcType="INTEGER" property="cash_user_id" />
    <result column="last_time" jdbcType="INTEGER" property="last_time" />
    <result column="order_cancel" jdbcType="BIT" property="order_cancel" />
    <result column="refuse_reason" jdbcType="VARCHAR" property="refuse_reason" />
    <result column="sub_order_id" jdbcType="INTEGER" property="sub_order_id" />
    <result column="is_freebuy" jdbcType="BIT" property="is_freebuy" />
  </resultMap>
  <resultMap extends="BaseResultMap" id="ResultMapWithBLOBs" type="com.pugutang.spring.boot.entity.OrderDoWithBLOBs">
    <result column="order_data" jdbcType="LONGVARCHAR" property="order_data" />
    <result column="mall_remark" jdbcType="LONGVARCHAR" property="mall_remark" />
    <result column="shop_remark" jdbcType="LONGVARCHAR" property="shop_remark" />
    <result column="store_remark" jdbcType="LONGVARCHAR" property="store_remark" />
  </resultMap>
  <sql id="Example_Where_Clause">
    <where>
      <foreach collection="oredCriteria" item="criteria" separator="or">
        <if test="criteria.valid">
          <trim prefix="(" prefixOverrides="and" suffix=")">
            <foreach collection="criteria.criteria" item="criterion">
              <choose>
                <when test="criterion.noValue">
                  and ${criterion.condition}
                </when>
                <when test="criterion.singleValue">
                  and ${criterion.condition} #{criterion.value}
                </when>
                <when test="criterion.betweenValue">
                  and ${criterion.condition} #{criterion.value} and #{criterion.secondValue}
                </when>
                <when test="criterion.listValue">
                  and ${criterion.condition}
                  <foreach close=")" collection="criterion.value" item="listItem" open="(" separator=",">
                    #{listItem}
                  </foreach>
                </when>
              </choose>
            </foreach>
          </trim>
        </if>
      </foreach>
    </where>
  </sql>
  <sql id="Update_By_Example_Where_Clause">
    <where>
      <foreach collection="example.oredCriteria" item="criteria" separator="or">
        <if test="criteria.valid">
          <trim prefix="(" prefixOverrides="and" suffix=")">
            <foreach collection="criteria.criteria" item="criterion">
              <choose>
                <when test="criterion.noValue">
                  and ${criterion.condition}
                </when>
                <when test="criterion.singleValue">
                  and ${criterion.condition} #{criterion.value}
                </when>
                <when test="criterion.betweenValue">
                  and ${criterion.condition} #{criterion.value} and #{criterion.secondValue}
                </when>
                <when test="criterion.listValue">
                  and ${criterion.condition}
                  <foreach close=")" collection="criterion.value" item="listItem" open="(" separator=",">
                    #{listItem}
                  </foreach>
                </when>
              </choose>
            </foreach>
          </trim>
        </if>
      </foreach>
    </where>
  </sql>
  <sql id="Base_Column_List">
    order_id, order_sn, parent_sn, user_id, order_status, shop_id, site_id, store_id, 
    pickup_id, shipping_status, pay_status, consignee, region_code, region_name, address, 
    address_lng, address_lat, receiving_mode, tel, email, postscript, best_time, pay_id, 
    pay_code, pay_name, pay_sn, is_cod, order_amount, order_points, money_paid, goods_amount, 
    inv_fee, shipping_fee, cash_more, discount_fee, change_amount, shipping_change, surplus, 
    user_surplus, user_surplus_limit, bonus_id, shop_bonus_id, bonus, shop_bonus, store_card_id, 
    store_card_price, integral, integral_money, give_integral, order_from, add_time, 
    pay_time, shipping_time, confirm_time, delay_days, order_type, service_mark, send_mark, 
    shipping_mark, buyer_type, evaluate_status, evaluate_time, end_time, is_distrib, 
    distrib_status, is_show, is_delete, close_reason, cash_user_id, last_time, order_cancel, 
    refuse_reason, sub_order_id, is_freebuy
  </sql>
  <sql id="Blob_Column_List">
    order_data, mall_remark, shop_remark, store_remark
  </sql>
  <select id="selectByExampleWithBLOBs" parameterType="com.pugutang.spring.boot.entity.OrderDoExample" resultMap="ResultMapWithBLOBs">
    select
    <if test="distinct">
      distinct
    </if>
    'true' as QUERYID,
    <include refid="Base_Column_List" />
    ,
    <include refid="Blob_Column_List" />
    from szy_order
    <if test="_parameter != null">
      <include refid="Example_Where_Clause" />
    </if>
    <if test="orderByClause != null">
      order by ${orderByClause}
    </if>
  </select>
  <select id="selectByExample" parameterType="com.pugutang.spring.boot.entity.OrderDoExample" resultMap="BaseResultMap">
    select
    <if test="distinct">
      distinct
    </if>
    'true' as QUERYID,
    <include refid="Base_Column_List" />
    from szy_order
    <if test="_parameter != null">
      <include refid="Example_Where_Clause" />
    </if>
    <if test="orderByClause != null">
      order by ${orderByClause}
    </if>
  </select>
  <select id="selectByPrimaryKey" parameterType="java.lang.Integer" resultMap="ResultMapWithBLOBs">
    select 
    <include refid="Base_Column_List" />
    ,
    <include refid="Blob_Column_List" />
    from szy_order
    where order_id = #{order_id,jdbcType=INTEGER}
  </select>
  <delete id="deleteByPrimaryKey" parameterType="java.lang.Integer">
    delete from szy_order
    where order_id = #{order_id,jdbcType=INTEGER}
  </delete>
  <insert id="insert" parameterType="com.pugutang.spring.boot.entity.OrderDoWithBLOBs">
    insert into szy_order (order_id, order_sn, parent_sn, 
      user_id, order_status, shop_id, 
      site_id, store_id, pickup_id, 
      shipping_status, pay_status, consignee, 
      region_code, region_name, address, 
      address_lng, address_lat, receiving_mode, 
      tel, email, postscript, 
      best_time, pay_id, pay_code, 
      pay_name, pay_sn, is_cod, 
      order_amount, order_points, money_paid, 
      goods_amount, inv_fee, shipping_fee, 
      cash_more, discount_fee, change_amount, 
      shipping_change, surplus, user_surplus, 
      user_surplus_limit, bonus_id, shop_bonus_id, 
      bonus, shop_bonus, store_card_id, 
      store_card_price, integral, integral_money, 
      give_integral, order_from, add_time, 
      pay_time, shipping_time, confirm_time, 
      delay_days, order_type, service_mark, 
      send_mark, shipping_mark, buyer_type, 
      evaluate_status, evaluate_time, end_time, 
      is_distrib, distrib_status, is_show, 
      is_delete, close_reason, cash_user_id, 
      last_time, order_cancel, refuse_reason, 
      sub_order_id, is_freebuy, order_data, 
      mall_remark, shop_remark, store_remark
      )
    values (#{order_id,jdbcType=INTEGER}, #{order_sn,jdbcType=VARCHAR}, #{parent_sn,jdbcType=VARCHAR}, 
      #{user_id,jdbcType=INTEGER}, #{order_status,jdbcType=BIT}, #{shop_id,jdbcType=INTEGER}, 
      #{site_id,jdbcType=INTEGER}, #{store_id,jdbcType=INTEGER}, #{pickup_id,jdbcType=INTEGER}, 
      #{shipping_status,jdbcType=BIT}, #{pay_status,jdbcType=BIT}, #{consignee,jdbcType=VARCHAR}, 
      #{region_code,jdbcType=VARCHAR}, #{region_name,jdbcType=VARCHAR}, #{address,jdbcType=VARCHAR}, 
      #{address_lng,jdbcType=VARCHAR}, #{address_lat,jdbcType=VARCHAR}, #{receiving_mode,jdbcType=BIT}, 
      #{tel,jdbcType=VARCHAR}, #{email,jdbcType=VARCHAR}, #{postscript,jdbcType=VARCHAR}, 
      #{best_time,jdbcType=VARCHAR}, #{pay_id,jdbcType=INTEGER}, #{pay_code,jdbcType=VARCHAR}, 
      #{pay_name,jdbcType=VARCHAR}, #{pay_sn,jdbcType=VARCHAR}, #{is_cod,jdbcType=BIT}, 
      #{order_amount,jdbcType=DECIMAL}, #{order_points,jdbcType=INTEGER}, #{money_paid,jdbcType=DECIMAL}, 
      #{goods_amount,jdbcType=DECIMAL}, #{inv_fee,jdbcType=DECIMAL}, #{shipping_fee,jdbcType=DECIMAL}, 
      #{cash_more,jdbcType=DECIMAL}, #{discount_fee,jdbcType=DECIMAL}, #{change_amount,jdbcType=DECIMAL}, 
      #{shipping_change,jdbcType=DECIMAL}, #{surplus,jdbcType=DECIMAL}, #{user_surplus,jdbcType=DECIMAL}, 
      #{user_surplus_limit,jdbcType=DECIMAL}, #{bonus_id,jdbcType=INTEGER}, #{shop_bonus_id,jdbcType=INTEGER}, 
      #{bonus,jdbcType=DECIMAL}, #{shop_bonus,jdbcType=DECIMAL}, #{store_card_id,jdbcType=INTEGER}, 
      #{store_card_price,jdbcType=DECIMAL}, #{integral,jdbcType=INTEGER}, #{integral_money,jdbcType=DECIMAL}, 
      #{give_integral,jdbcType=INTEGER}, #{order_from,jdbcType=VARCHAR}, #{add_time,jdbcType=INTEGER}, 
      #{pay_time,jdbcType=INTEGER}, #{shipping_time,jdbcType=INTEGER}, #{confirm_time,jdbcType=INTEGER}, 
      #{delay_days,jdbcType=BIT}, #{order_type,jdbcType=BIT}, #{service_mark,jdbcType=BIT}, 
      #{send_mark,jdbcType=BIT}, #{shipping_mark,jdbcType=BIT}, #{buyer_type,jdbcType=BIT}, 
      #{evaluate_status,jdbcType=BIT}, #{evaluate_time,jdbcType=INTEGER}, #{end_time,jdbcType=INTEGER}, 
      #{is_distrib,jdbcType=BIT}, #{distrib_status,jdbcType=BIT}, #{is_show,jdbcType=VARCHAR}, 
      #{is_delete,jdbcType=BIT}, #{close_reason,jdbcType=VARCHAR}, #{cash_user_id,jdbcType=INTEGER}, 
      #{last_time,jdbcType=INTEGER}, #{order_cancel,jdbcType=BIT}, #{refuse_reason,jdbcType=VARCHAR}, 
      #{sub_order_id,jdbcType=INTEGER}, #{is_freebuy,jdbcType=BIT}, #{order_data,jdbcType=LONGVARCHAR}, 
      #{mall_remark,jdbcType=LONGVARCHAR}, #{shop_remark,jdbcType=LONGVARCHAR}, #{store_remark,jdbcType=LONGVARCHAR}
      )
  </insert>
  <insert id="insertSelective" parameterType="com.pugutang.spring.boot.entity.OrderDoWithBLOBs">
    insert into szy_order
    <trim prefix="(" suffix=")" suffixOverrides=",">
      <if test="order_id != null">
        order_id,
      </if>
      <if test="order_sn != null">
        order_sn,
      </if>
      <if test="parent_sn != null">
        parent_sn,
      </if>
      <if test="user_id != null">
        user_id,
      </if>
      <if test="order_status != null">
        order_status,
      </if>
      <if test="shop_id != null">
        shop_id,
      </if>
      <if test="site_id != null">
        site_id,
      </if>
      <if test="store_id != null">
        store_id,
      </if>
      <if test="pickup_id != null">
        pickup_id,
      </if>
      <if test="shipping_status != null">
        shipping_status,
      </if>
      <if test="pay_status != null">
        pay_status,
      </if>
      <if test="consignee != null">
        consignee,
      </if>
      <if test="region_code != null">
        region_code,
      </if>
      <if test="region_name != null">
        region_name,
      </if>
      <if test="address != null">
        address,
      </if>
      <if test="address_lng != null">
        address_lng,
      </if>
      <if test="address_lat != null">
        address_lat,
      </if>
      <if test="receiving_mode != null">
        receiving_mode,
      </if>
      <if test="tel != null">
        tel,
      </if>
      <if test="email != null">
        email,
      </if>
      <if test="postscript != null">
        postscript,
      </if>
      <if test="best_time != null">
        best_time,
      </if>
      <if test="pay_id != null">
        pay_id,
      </if>
      <if test="pay_code != null">
        pay_code,
      </if>
      <if test="pay_name != null">
        pay_name,
      </if>
      <if test="pay_sn != null">
        pay_sn,
      </if>
      <if test="is_cod != null">
        is_cod,
      </if>
      <if test="order_amount != null">
        order_amount,
      </if>
      <if test="order_points != null">
        order_points,
      </if>
      <if test="money_paid != null">
        money_paid,
      </if>
      <if test="goods_amount != null">
        goods_amount,
      </if>
      <if test="inv_fee != null">
        inv_fee,
      </if>
      <if test="shipping_fee != null">
        shipping_fee,
      </if>
      <if test="cash_more != null">
        cash_more,
      </if>
      <if test="discount_fee != null">
        discount_fee,
      </if>
      <if test="change_amount != null">
        change_amount,
      </if>
      <if test="shipping_change != null">
        shipping_change,
      </if>
      <if test="surplus != null">
        surplus,
      </if>
      <if test="user_surplus != null">
        user_surplus,
      </if>
      <if test="user_surplus_limit != null">
        user_surplus_limit,
      </if>
      <if test="bonus_id != null">
        bonus_id,
      </if>
      <if test="shop_bonus_id != null">
        shop_bonus_id,
      </if>
      <if test="bonus != null">
        bonus,
      </if>
      <if test="shop_bonus != null">
        shop_bonus,
      </if>
      <if test="store_card_id != null">
        store_card_id,
      </if>
      <if test="store_card_price != null">
        store_card_price,
      </if>
      <if test="integral != null">
        integral,
      </if>
      <if test="integral_money != null">
        integral_money,
      </if>
      <if test="give_integral != null">
        give_integral,
      </if>
      <if test="order_from != null">
        order_from,
      </if>
      <if test="add_time != null">
        add_time,
      </if>
      <if test="pay_time != null">
        pay_time,
      </if>
      <if test="shipping_time != null">
        shipping_time,
      </if>
      <if test="confirm_time != null">
        confirm_time,
      </if>
      <if test="delay_days != null">
        delay_days,
      </if>
      <if test="order_type != null">
        order_type,
      </if>
      <if test="service_mark != null">
        service_mark,
      </if>
      <if test="send_mark != null">
        send_mark,
      </if>
      <if test="shipping_mark != null">
        shipping_mark,
      </if>
      <if test="buyer_type != null">
        buyer_type,
      </if>
      <if test="evaluate_status != null">
        evaluate_status,
      </if>
      <if test="evaluate_time != null">
        evaluate_time,
      </if>
      <if test="end_time != null">
        end_time,
      </if>
      <if test="is_distrib != null">
        is_distrib,
      </if>
      <if test="distrib_status != null">
        distrib_status,
      </if>
      <if test="is_show != null">
        is_show,
      </if>
      <if test="is_delete != null">
        is_delete,
      </if>
      <if test="close_reason != null">
        close_reason,
      </if>
      <if test="cash_user_id != null">
        cash_user_id,
      </if>
      <if test="last_time != null">
        last_time,
      </if>
      <if test="order_cancel != null">
        order_cancel,
      </if>
      <if test="refuse_reason != null">
        refuse_reason,
      </if>
      <if test="sub_order_id != null">
        sub_order_id,
      </if>
      <if test="is_freebuy != null">
        is_freebuy,
      </if>
      <if test="order_data != null">
        order_data,
      </if>
      <if test="mall_remark != null">
        mall_remark,
      </if>
      <if test="shop_remark != null">
        shop_remark,
      </if>
      <if test="store_remark != null">
        store_remark,
      </if>
    </trim>
    <trim prefix="values (" suffix=")" suffixOverrides=",">
      <if test="order_id != null">
        #{order_id,jdbcType=INTEGER},
      </if>
      <if test="order_sn != null">
        #{order_sn,jdbcType=VARCHAR},
      </if>
      <if test="parent_sn != null">
        #{parent_sn,jdbcType=VARCHAR},
      </if>
      <if test="user_id != null">
        #{user_id,jdbcType=INTEGER},
      </if>
      <if test="order_status != null">
        #{order_status,jdbcType=BIT},
      </if>
      <if test="shop_id != null">
        #{shop_id,jdbcType=INTEGER},
      </if>
      <if test="site_id != null">
        #{site_id,jdbcType=INTEGER},
      </if>
      <if test="store_id != null">
        #{store_id,jdbcType=INTEGER},
      </if>
      <if test="pickup_id != null">
        #{pickup_id,jdbcType=INTEGER},
      </if>
      <if test="shipping_status != null">
        #{shipping_status,jdbcType=BIT},
      </if>
      <if test="pay_status != null">
        #{pay_status,jdbcType=BIT},
      </if>
      <if test="consignee != null">
        #{consignee,jdbcType=VARCHAR},
      </if>
      <if test="region_code != null">
        #{region_code,jdbcType=VARCHAR},
      </if>
      <if test="region_name != null">
        #{region_name,jdbcType=VARCHAR},
      </if>
      <if test="address != null">
        #{address,jdbcType=VARCHAR},
      </if>
      <if test="address_lng != null">
        #{address_lng,jdbcType=VARCHAR},
      </if>
      <if test="address_lat != null">
        #{address_lat,jdbcType=VARCHAR},
      </if>
      <if test="receiving_mode != null">
        #{receiving_mode,jdbcType=BIT},
      </if>
      <if test="tel != null">
        #{tel,jdbcType=VARCHAR},
      </if>
      <if test="email != null">
        #{email,jdbcType=VARCHAR},
      </if>
      <if test="postscript != null">
        #{postscript,jdbcType=VARCHAR},
      </if>
      <if test="best_time != null">
        #{best_time,jdbcType=VARCHAR},
      </if>
      <if test="pay_id != null">
        #{pay_id,jdbcType=INTEGER},
      </if>
      <if test="pay_code != null">
        #{pay_code,jdbcType=VARCHAR},
      </if>
      <if test="pay_name != null">
        #{pay_name,jdbcType=VARCHAR},
      </if>
      <if test="pay_sn != null">
        #{pay_sn,jdbcType=VARCHAR},
      </if>
      <if test="is_cod != null">
        #{is_cod,jdbcType=BIT},
      </if>
      <if test="order_amount != null">
        #{order_amount,jdbcType=DECIMAL},
      </if>
      <if test="order_points != null">
        #{order_points,jdbcType=INTEGER},
      </if>
      <if test="money_paid != null">
        #{money_paid,jdbcType=DECIMAL},
      </if>
      <if test="goods_amount != null">
        #{goods_amount,jdbcType=DECIMAL},
      </if>
      <if test="inv_fee != null">
        #{inv_fee,jdbcType=DECIMAL},
      </if>
      <if test="shipping_fee != null">
        #{shipping_fee,jdbcType=DECIMAL},
      </if>
      <if test="cash_more != null">
        #{cash_more,jdbcType=DECIMAL},
      </if>
      <if test="discount_fee != null">
        #{discount_fee,jdbcType=DECIMAL},
      </if>
      <if test="change_amount != null">
        #{change_amount,jdbcType=DECIMAL},
      </if>
      <if test="shipping_change != null">
        #{shipping_change,jdbcType=DECIMAL},
      </if>
      <if test="surplus != null">
        #{surplus,jdbcType=DECIMAL},
      </if>
      <if test="user_surplus != null">
        #{user_surplus,jdbcType=DECIMAL},
      </if>
      <if test="user_surplus_limit != null">
        #{user_surplus_limit,jdbcType=DECIMAL},
      </if>
      <if test="bonus_id != null">
        #{bonus_id,jdbcType=INTEGER},
      </if>
      <if test="shop_bonus_id != null">
        #{shop_bonus_id,jdbcType=INTEGER},
      </if>
      <if test="bonus != null">
        #{bonus,jdbcType=DECIMAL},
      </if>
      <if test="shop_bonus != null">
        #{shop_bonus,jdbcType=DECIMAL},
      </if>
      <if test="store_card_id != null">
        #{store_card_id,jdbcType=INTEGER},
      </if>
      <if test="store_card_price != null">
        #{store_card_price,jdbcType=DECIMAL},
      </if>
      <if test="integral != null">
        #{integral,jdbcType=INTEGER},
      </if>
      <if test="integral_money != null">
        #{integral_money,jdbcType=DECIMAL},
      </if>
      <if test="give_integral != null">
        #{give_integral,jdbcType=INTEGER},
      </if>
      <if test="order_from != null">
        #{order_from,jdbcType=VARCHAR},
      </if>
      <if test="add_time != null">
        #{add_time,jdbcType=INTEGER},
      </if>
      <if test="pay_time != null">
        #{pay_time,jdbcType=INTEGER},
      </if>
      <if test="shipping_time != null">
        #{shipping_time,jdbcType=INTEGER},
      </if>
      <if test="confirm_time != null">
        #{confirm_time,jdbcType=INTEGER},
      </if>
      <if test="delay_days != null">
        #{delay_days,jdbcType=BIT},
      </if>
      <if test="order_type != null">
        #{order_type,jdbcType=BIT},
      </if>
      <if test="service_mark != null">
        #{service_mark,jdbcType=BIT},
      </if>
      <if test="send_mark != null">
        #{send_mark,jdbcType=BIT},
      </if>
      <if test="shipping_mark != null">
        #{shipping_mark,jdbcType=BIT},
      </if>
      <if test="buyer_type != null">
        #{buyer_type,jdbcType=BIT},
      </if>
      <if test="evaluate_status != null">
        #{evaluate_status,jdbcType=BIT},
      </if>
      <if test="evaluate_time != null">
        #{evaluate_time,jdbcType=INTEGER},
      </if>
      <if test="end_time != null">
        #{end_time,jdbcType=INTEGER},
      </if>
      <if test="is_distrib != null">
        #{is_distrib,jdbcType=BIT},
      </if>
      <if test="distrib_status != null">
        #{distrib_status,jdbcType=BIT},
      </if>
      <if test="is_show != null">
        #{is_show,jdbcType=VARCHAR},
      </if>
      <if test="is_delete != null">
        #{is_delete,jdbcType=BIT},
      </if>
      <if test="close_reason != null">
        #{close_reason,jdbcType=VARCHAR},
      </if>
      <if test="cash_user_id != null">
        #{cash_user_id,jdbcType=INTEGER},
      </if>
      <if test="last_time != null">
        #{last_time,jdbcType=INTEGER},
      </if>
      <if test="order_cancel != null">
        #{order_cancel,jdbcType=BIT},
      </if>
      <if test="refuse_reason != null">
        #{refuse_reason,jdbcType=VARCHAR},
      </if>
      <if test="sub_order_id != null">
        #{sub_order_id,jdbcType=INTEGER},
      </if>
      <if test="is_freebuy != null">
        #{is_freebuy,jdbcType=BIT},
      </if>
      <if test="order_data != null">
        #{order_data,jdbcType=LONGVARCHAR},
      </if>
      <if test="mall_remark != null">
        #{mall_remark,jdbcType=LONGVARCHAR},
      </if>
      <if test="shop_remark != null">
        #{shop_remark,jdbcType=LONGVARCHAR},
      </if>
      <if test="store_remark != null">
        #{store_remark,jdbcType=LONGVARCHAR},
      </if>
    </trim>
  </insert>
  <select id="countByExample" parameterType="com.pugutang.spring.boot.entity.OrderDoExample" resultType="java.lang.Long">
    select count(*) from szy_order
    <if test="_parameter != null">
      <include refid="Example_Where_Clause" />
    </if>
  </select>
  <update id="updateByExampleSelective" parameterType="map">
    update szy_order
    <set>
      <if test="record.order_id != null">
        order_id = #{record.order_id,jdbcType=INTEGER},
      </if>
      <if test="record.order_sn != null">
        order_sn = #{record.order_sn,jdbcType=VARCHAR},
      </if>
      <if test="record.parent_sn != null">
        parent_sn = #{record.parent_sn,jdbcType=VARCHAR},
      </if>
      <if test="record.user_id != null">
        user_id = #{record.user_id,jdbcType=INTEGER},
      </if>
      <if test="record.order_status != null">
        order_status = #{record.order_status,jdbcType=BIT},
      </if>
      <if test="record.shop_id != null">
        shop_id = #{record.shop_id,jdbcType=INTEGER},
      </if>
      <if test="record.site_id != null">
        site_id = #{record.site_id,jdbcType=INTEGER},
      </if>
      <if test="record.store_id != null">
        store_id = #{record.store_id,jdbcType=INTEGER},
      </if>
      <if test="record.pickup_id != null">
        pickup_id = #{record.pickup_id,jdbcType=INTEGER},
      </if>
      <if test="record.shipping_status != null">
        shipping_status = #{record.shipping_status,jdbcType=BIT},
      </if>
      <if test="record.pay_status != null">
        pay_status = #{record.pay_status,jdbcType=BIT},
      </if>
      <if test="record.consignee != null">
        consignee = #{record.consignee,jdbcType=VARCHAR},
      </if>
      <if test="record.region_code != null">
        region_code = #{record.region_code,jdbcType=VARCHAR},
      </if>
      <if test="record.region_name != null">
        region_name = #{record.region_name,jdbcType=VARCHAR},
      </if>
      <if test="record.address != null">
        address = #{record.address,jdbcType=VARCHAR},
      </if>
      <if test="record.address_lng != null">
        address_lng = #{record.address_lng,jdbcType=VARCHAR},
      </if>
      <if test="record.address_lat != null">
        address_lat = #{record.address_lat,jdbcType=VARCHAR},
      </if>
      <if test="record.receiving_mode != null">
        receiving_mode = #{record.receiving_mode,jdbcType=BIT},
      </if>
      <if test="record.tel != null">
        tel = #{record.tel,jdbcType=VARCHAR},
      </if>
      <if test="record.email != null">
        email = #{record.email,jdbcType=VARCHAR},
      </if>
      <if test="record.postscript != null">
        postscript = #{record.postscript,jdbcType=VARCHAR},
      </if>
      <if test="record.best_time != null">
        best_time = #{record.best_time,jdbcType=VARCHAR},
      </if>
      <if test="record.pay_id != null">
        pay_id = #{record.pay_id,jdbcType=INTEGER},
      </if>
      <if test="record.pay_code != null">
        pay_code = #{record.pay_code,jdbcType=VARCHAR},
      </if>
      <if test="record.pay_name != null">
        pay_name = #{record.pay_name,jdbcType=VARCHAR},
      </if>
      <if test="record.pay_sn != null">
        pay_sn = #{record.pay_sn,jdbcType=VARCHAR},
      </if>
      <if test="record.is_cod != null">
        is_cod = #{record.is_cod,jdbcType=BIT},
      </if>
      <if test="record.order_amount != null">
        order_amount = #{record.order_amount,jdbcType=DECIMAL},
      </if>
      <if test="record.order_points != null">
        order_points = #{record.order_points,jdbcType=INTEGER},
      </if>
      <if test="record.money_paid != null">
        money_paid = #{record.money_paid,jdbcType=DECIMAL},
      </if>
      <if test="record.goods_amount != null">
        goods_amount = #{record.goods_amount,jdbcType=DECIMAL},
      </if>
      <if test="record.inv_fee != null">
        inv_fee = #{record.inv_fee,jdbcType=DECIMAL},
      </if>
      <if test="record.shipping_fee != null">
        shipping_fee = #{record.shipping_fee,jdbcType=DECIMAL},
      </if>
      <if test="record.cash_more != null">
        cash_more = #{record.cash_more,jdbcType=DECIMAL},
      </if>
      <if test="record.discount_fee != null">
        discount_fee = #{record.discount_fee,jdbcType=DECIMAL},
      </if>
      <if test="record.change_amount != null">
        change_amount = #{record.change_amount,jdbcType=DECIMAL},
      </if>
      <if test="record.shipping_change != null">
        shipping_change = #{record.shipping_change,jdbcType=DECIMAL},
      </if>
      <if test="record.surplus != null">
        surplus = #{record.surplus,jdbcType=DECIMAL},
      </if>
      <if test="record.user_surplus != null">
        user_surplus = #{record.user_surplus,jdbcType=DECIMAL},
      </if>
      <if test="record.user_surplus_limit != null">
        user_surplus_limit = #{record.user_surplus_limit,jdbcType=DECIMAL},
      </if>
      <if test="record.bonus_id != null">
        bonus_id = #{record.bonus_id,jdbcType=INTEGER},
      </if>
      <if test="record.shop_bonus_id != null">
        shop_bonus_id = #{record.shop_bonus_id,jdbcType=INTEGER},
      </if>
      <if test="record.bonus != null">
        bonus = #{record.bonus,jdbcType=DECIMAL},
      </if>
      <if test="record.shop_bonus != null">
        shop_bonus = #{record.shop_bonus,jdbcType=DECIMAL},
      </if>
      <if test="record.store_card_id != null">
        store_card_id = #{record.store_card_id,jdbcType=INTEGER},
      </if>
      <if test="record.store_card_price != null">
        store_card_price = #{record.store_card_price,jdbcType=DECIMAL},
      </if>
      <if test="record.integral != null">
        integral = #{record.integral,jdbcType=INTEGER},
      </if>
      <if test="record.integral_money != null">
        integral_money = #{record.integral_money,jdbcType=DECIMAL},
      </if>
      <if test="record.give_integral != null">
        give_integral = #{record.give_integral,jdbcType=INTEGER},
      </if>
      <if test="record.order_from != null">
        order_from = #{record.order_from,jdbcType=VARCHAR},
      </if>
      <if test="record.add_time != null">
        add_time = #{record.add_time,jdbcType=INTEGER},
      </if>
      <if test="record.pay_time != null">
        pay_time = #{record.pay_time,jdbcType=INTEGER},
      </if>
      <if test="record.shipping_time != null">
        shipping_time = #{record.shipping_time,jdbcType=INTEGER},
      </if>
      <if test="record.confirm_time != null">
        confirm_time = #{record.confirm_time,jdbcType=INTEGER},
      </if>
      <if test="record.delay_days != null">
        delay_days = #{record.delay_days,jdbcType=BIT},
      </if>
      <if test="record.order_type != null">
        order_type = #{record.order_type,jdbcType=BIT},
      </if>
      <if test="record.service_mark != null">
        service_mark = #{record.service_mark,jdbcType=BIT},
      </if>
      <if test="record.send_mark != null">
        send_mark = #{record.send_mark,jdbcType=BIT},
      </if>
      <if test="record.shipping_mark != null">
        shipping_mark = #{record.shipping_mark,jdbcType=BIT},
      </if>
      <if test="record.buyer_type != null">
        buyer_type = #{record.buyer_type,jdbcType=BIT},
      </if>
      <if test="record.evaluate_status != null">
        evaluate_status = #{record.evaluate_status,jdbcType=BIT},
      </if>
      <if test="record.evaluate_time != null">
        evaluate_time = #{record.evaluate_time,jdbcType=INTEGER},
      </if>
      <if test="record.end_time != null">
        end_time = #{record.end_time,jdbcType=INTEGER},
      </if>
      <if test="record.is_distrib != null">
        is_distrib = #{record.is_distrib,jdbcType=BIT},
      </if>
      <if test="record.distrib_status != null">
        distrib_status = #{record.distrib_status,jdbcType=BIT},
      </if>
      <if test="record.is_show != null">
        is_show = #{record.is_show,jdbcType=VARCHAR},
      </if>
      <if test="record.is_delete != null">
        is_delete = #{record.is_delete,jdbcType=BIT},
      </if>
      <if test="record.close_reason != null">
        close_reason = #{record.close_reason,jdbcType=VARCHAR},
      </if>
      <if test="record.cash_user_id != null">
        cash_user_id = #{record.cash_user_id,jdbcType=INTEGER},
      </if>
      <if test="record.last_time != null">
        last_time = #{record.last_time,jdbcType=INTEGER},
      </if>
      <if test="record.order_cancel != null">
        order_cancel = #{record.order_cancel,jdbcType=BIT},
      </if>
      <if test="record.refuse_reason != null">
        refuse_reason = #{record.refuse_reason,jdbcType=VARCHAR},
      </if>
      <if test="record.sub_order_id != null">
        sub_order_id = #{record.sub_order_id,jdbcType=INTEGER},
      </if>
      <if test="record.is_freebuy != null">
        is_freebuy = #{record.is_freebuy,jdbcType=BIT},
      </if>
      <if test="record.order_data != null">
        order_data = #{record.order_data,jdbcType=LONGVARCHAR},
      </if>
      <if test="record.mall_remark != null">
        mall_remark = #{record.mall_remark,jdbcType=LONGVARCHAR},
      </if>
      <if test="record.shop_remark != null">
        shop_remark = #{record.shop_remark,jdbcType=LONGVARCHAR},
      </if>
      <if test="record.store_remark != null">
        store_remark = #{record.store_remark,jdbcType=LONGVARCHAR},
      </if>
    </set>
    <if test="_parameter != null">
      <include refid="Update_By_Example_Where_Clause" />
    </if>
  </update>
  <update id="updateByExampleWithBLOBs" parameterType="map">
    update szy_order
    set order_id = #{record.order_id,jdbcType=INTEGER},
      order_sn = #{record.order_sn,jdbcType=VARCHAR},
      parent_sn = #{record.parent_sn,jdbcType=VARCHAR},
      user_id = #{record.user_id,jdbcType=INTEGER},
      order_status = #{record.order_status,jdbcType=BIT},
      shop_id = #{record.shop_id,jdbcType=INTEGER},
      site_id = #{record.site_id,jdbcType=INTEGER},
      store_id = #{record.store_id,jdbcType=INTEGER},
      pickup_id = #{record.pickup_id,jdbcType=INTEGER},
      shipping_status = #{record.shipping_status,jdbcType=BIT},
      pay_status = #{record.pay_status,jdbcType=BIT},
      consignee = #{record.consignee,jdbcType=VARCHAR},
      region_code = #{record.region_code,jdbcType=VARCHAR},
      region_name = #{record.region_name,jdbcType=VARCHAR},
      address = #{record.address,jdbcType=VARCHAR},
      address_lng = #{record.address_lng,jdbcType=VARCHAR},
      address_lat = #{record.address_lat,jdbcType=VARCHAR},
      receiving_mode = #{record.receiving_mode,jdbcType=BIT},
      tel = #{record.tel,jdbcType=VARCHAR},
      email = #{record.email,jdbcType=VARCHAR},
      postscript = #{record.postscript,jdbcType=VARCHAR},
      best_time = #{record.best_time,jdbcType=VARCHAR},
      pay_id = #{record.pay_id,jdbcType=INTEGER},
      pay_code = #{record.pay_code,jdbcType=VARCHAR},
      pay_name = #{record.pay_name,jdbcType=VARCHAR},
      pay_sn = #{record.pay_sn,jdbcType=VARCHAR},
      is_cod = #{record.is_cod,jdbcType=BIT},
      order_amount = #{record.order_amount,jdbcType=DECIMAL},
      order_points = #{record.order_points,jdbcType=INTEGER},
      money_paid = #{record.money_paid,jdbcType=DECIMAL},
      goods_amount = #{record.goods_amount,jdbcType=DECIMAL},
      inv_fee = #{record.inv_fee,jdbcType=DECIMAL},
      shipping_fee = #{record.shipping_fee,jdbcType=DECIMAL},
      cash_more = #{record.cash_more,jdbcType=DECIMAL},
      discount_fee = #{record.discount_fee,jdbcType=DECIMAL},
      change_amount = #{record.change_amount,jdbcType=DECIMAL},
      shipping_change = #{record.shipping_change,jdbcType=DECIMAL},
      surplus = #{record.surplus,jdbcType=DECIMAL},
      user_surplus = #{record.user_surplus,jdbcType=DECIMAL},
      user_surplus_limit = #{record.user_surplus_limit,jdbcType=DECIMAL},
      bonus_id = #{record.bonus_id,jdbcType=INTEGER},
      shop_bonus_id = #{record.shop_bonus_id,jdbcType=INTEGER},
      bonus = #{record.bonus,jdbcType=DECIMAL},
      shop_bonus = #{record.shop_bonus,jdbcType=DECIMAL},
      store_card_id = #{record.store_card_id,jdbcType=INTEGER},
      store_card_price = #{record.store_card_price,jdbcType=DECIMAL},
      integral = #{record.integral,jdbcType=INTEGER},
      integral_money = #{record.integral_money,jdbcType=DECIMAL},
      give_integral = #{record.give_integral,jdbcType=INTEGER},
      order_from = #{record.order_from,jdbcType=VARCHAR},
      add_time = #{record.add_time,jdbcType=INTEGER},
      pay_time = #{record.pay_time,jdbcType=INTEGER},
      shipping_time = #{record.shipping_time,jdbcType=INTEGER},
      confirm_time = #{record.confirm_time,jdbcType=INTEGER},
      delay_days = #{record.delay_days,jdbcType=BIT},
      order_type = #{record.order_type,jdbcType=BIT},
      service_mark = #{record.service_mark,jdbcType=BIT},
      send_mark = #{record.send_mark,jdbcType=BIT},
      shipping_mark = #{record.shipping_mark,jdbcType=BIT},
      buyer_type = #{record.buyer_type,jdbcType=BIT},
      evaluate_status = #{record.evaluate_status,jdbcType=BIT},
      evaluate_time = #{record.evaluate_time,jdbcType=INTEGER},
      end_time = #{record.end_time,jdbcType=INTEGER},
      is_distrib = #{record.is_distrib,jdbcType=BIT},
      distrib_status = #{record.distrib_status,jdbcType=BIT},
      is_show = #{record.is_show,jdbcType=VARCHAR},
      is_delete = #{record.is_delete,jdbcType=BIT},
      close_reason = #{record.close_reason,jdbcType=VARCHAR},
      cash_user_id = #{record.cash_user_id,jdbcType=INTEGER},
      last_time = #{record.last_time,jdbcType=INTEGER},
      order_cancel = #{record.order_cancel,jdbcType=BIT},
      refuse_reason = #{record.refuse_reason,jdbcType=VARCHAR},
      sub_order_id = #{record.sub_order_id,jdbcType=INTEGER},
      is_freebuy = #{record.is_freebuy,jdbcType=BIT},
      order_data = #{record.order_data,jdbcType=LONGVARCHAR},
      mall_remark = #{record.mall_remark,jdbcType=LONGVARCHAR},
      shop_remark = #{record.shop_remark,jdbcType=LONGVARCHAR},
      store_remark = #{record.store_remark,jdbcType=LONGVARCHAR}
    <if test="_parameter != null">
      <include refid="Update_By_Example_Where_Clause" />
    </if>
  </update>
  <update id="updateByExample" parameterType="map">
    update szy_order
    set order_id = #{record.order_id,jdbcType=INTEGER},
      order_sn = #{record.order_sn,jdbcType=VARCHAR},
      parent_sn = #{record.parent_sn,jdbcType=VARCHAR},
      user_id = #{record.user_id,jdbcType=INTEGER},
      order_status = #{record.order_status,jdbcType=BIT},
      shop_id = #{record.shop_id,jdbcType=INTEGER},
      site_id = #{record.site_id,jdbcType=INTEGER},
      store_id = #{record.store_id,jdbcType=INTEGER},
      pickup_id = #{record.pickup_id,jdbcType=INTEGER},
      shipping_status = #{record.shipping_status,jdbcType=BIT},
      pay_status = #{record.pay_status,jdbcType=BIT},
      consignee = #{record.consignee,jdbcType=VARCHAR},
      region_code = #{record.region_code,jdbcType=VARCHAR},
      region_name = #{record.region_name,jdbcType=VARCHAR},
      address = #{record.address,jdbcType=VARCHAR},
      address_lng = #{record.address_lng,jdbcType=VARCHAR},
      address_lat = #{record.address_lat,jdbcType=VARCHAR},
      receiving_mode = #{record.receiving_mode,jdbcType=BIT},
      tel = #{record.tel,jdbcType=VARCHAR},
      email = #{record.email,jdbcType=VARCHAR},
      postscript = #{record.postscript,jdbcType=VARCHAR},
      best_time = #{record.best_time,jdbcType=VARCHAR},
      pay_id = #{record.pay_id,jdbcType=INTEGER},
      pay_code = #{record.pay_code,jdbcType=VARCHAR},
      pay_name = #{record.pay_name,jdbcType=VARCHAR},
      pay_sn = #{record.pay_sn,jdbcType=VARCHAR},
      is_cod = #{record.is_cod,jdbcType=BIT},
      order_amount = #{record.order_amount,jdbcType=DECIMAL},
      order_points = #{record.order_points,jdbcType=INTEGER},
      money_paid = #{record.money_paid,jdbcType=DECIMAL},
      goods_amount = #{record.goods_amount,jdbcType=DECIMAL},
      inv_fee = #{record.inv_fee,jdbcType=DECIMAL},
      shipping_fee = #{record.shipping_fee,jdbcType=DECIMAL},
      cash_more = #{record.cash_more,jdbcType=DECIMAL},
      discount_fee = #{record.discount_fee,jdbcType=DECIMAL},
      change_amount = #{record.change_amount,jdbcType=DECIMAL},
      shipping_change = #{record.shipping_change,jdbcType=DECIMAL},
      surplus = #{record.surplus,jdbcType=DECIMAL},
      user_surplus = #{record.user_surplus,jdbcType=DECIMAL},
      user_surplus_limit = #{record.user_surplus_limit,jdbcType=DECIMAL},
      bonus_id = #{record.bonus_id,jdbcType=INTEGER},
      shop_bonus_id = #{record.shop_bonus_id,jdbcType=INTEGER},
      bonus = #{record.bonus,jdbcType=DECIMAL},
      shop_bonus = #{record.shop_bonus,jdbcType=DECIMAL},
      store_card_id = #{record.store_card_id,jdbcType=INTEGER},
      store_card_price = #{record.store_card_price,jdbcType=DECIMAL},
      integral = #{record.integral,jdbcType=INTEGER},
      integral_money = #{record.integral_money,jdbcType=DECIMAL},
      give_integral = #{record.give_integral,jdbcType=INTEGER},
      order_from = #{record.order_from,jdbcType=VARCHAR},
      add_time = #{record.add_time,jdbcType=INTEGER},
      pay_time = #{record.pay_time,jdbcType=INTEGER},
      shipping_time = #{record.shipping_time,jdbcType=INTEGER},
      confirm_time = #{record.confirm_time,jdbcType=INTEGER},
      delay_days = #{record.delay_days,jdbcType=BIT},
      order_type = #{record.order_type,jdbcType=BIT},
      service_mark = #{record.service_mark,jdbcType=BIT},
      send_mark = #{record.send_mark,jdbcType=BIT},
      shipping_mark = #{record.shipping_mark,jdbcType=BIT},
      buyer_type = #{record.buyer_type,jdbcType=BIT},
      evaluate_status = #{record.evaluate_status,jdbcType=BIT},
      evaluate_time = #{record.evaluate_time,jdbcType=INTEGER},
      end_time = #{record.end_time,jdbcType=INTEGER},
      is_distrib = #{record.is_distrib,jdbcType=BIT},
      distrib_status = #{record.distrib_status,jdbcType=BIT},
      is_show = #{record.is_show,jdbcType=VARCHAR},
      is_delete = #{record.is_delete,jdbcType=BIT},
      close_reason = #{record.close_reason,jdbcType=VARCHAR},
      cash_user_id = #{record.cash_user_id,jdbcType=INTEGER},
      last_time = #{record.last_time,jdbcType=INTEGER},
      order_cancel = #{record.order_cancel,jdbcType=BIT},
      refuse_reason = #{record.refuse_reason,jdbcType=VARCHAR},
      sub_order_id = #{record.sub_order_id,jdbcType=INTEGER},
      is_freebuy = #{record.is_freebuy,jdbcType=BIT}
    <if test="_parameter != null">
      <include refid="Update_By_Example_Where_Clause" />
    </if>
  </update>
  <update id="updateByPrimaryKeySelective" parameterType="com.pugutang.spring.boot.entity.OrderDoWithBLOBs">
    update szy_order
    <set>
      <if test="order_sn != null">
        order_sn = #{order_sn,jdbcType=VARCHAR},
      </if>
      <if test="parent_sn != null">
        parent_sn = #{parent_sn,jdbcType=VARCHAR},
      </if>
      <if test="user_id != null">
        user_id = #{user_id,jdbcType=INTEGER},
      </if>
      <if test="order_status != null">
        order_status = #{order_status,jdbcType=BIT},
      </if>
      <if test="shop_id != null">
        shop_id = #{shop_id,jdbcType=INTEGER},
      </if>
      <if test="site_id != null">
        site_id = #{site_id,jdbcType=INTEGER},
      </if>
      <if test="store_id != null">
        store_id = #{store_id,jdbcType=INTEGER},
      </if>
      <if test="pickup_id != null">
        pickup_id = #{pickup_id,jdbcType=INTEGER},
      </if>
      <if test="shipping_status != null">
        shipping_status = #{shipping_status,jdbcType=BIT},
      </if>
      <if test="pay_status != null">
        pay_status = #{pay_status,jdbcType=BIT},
      </if>
      <if test="consignee != null">
        consignee = #{consignee,jdbcType=VARCHAR},
      </if>
      <if test="region_code != null">
        region_code = #{region_code,jdbcType=VARCHAR},
      </if>
      <if test="region_name != null">
        region_name = #{region_name,jdbcType=VARCHAR},
      </if>
      <if test="address != null">
        address = #{address,jdbcType=VARCHAR},
      </if>
      <if test="address_lng != null">
        address_lng = #{address_lng,jdbcType=VARCHAR},
      </if>
      <if test="address_lat != null">
        address_lat = #{address_lat,jdbcType=VARCHAR},
      </if>
      <if test="receiving_mode != null">
        receiving_mode = #{receiving_mode,jdbcType=BIT},
      </if>
      <if test="tel != null">
        tel = #{tel,jdbcType=VARCHAR},
      </if>
      <if test="email != null">
        email = #{email,jdbcType=VARCHAR},
      </if>
      <if test="postscript != null">
        postscript = #{postscript,jdbcType=VARCHAR},
      </if>
      <if test="best_time != null">
        best_time = #{best_time,jdbcType=VARCHAR},
      </if>
      <if test="pay_id != null">
        pay_id = #{pay_id,jdbcType=INTEGER},
      </if>
      <if test="pay_code != null">
        pay_code = #{pay_code,jdbcType=VARCHAR},
      </if>
      <if test="pay_name != null">
        pay_name = #{pay_name,jdbcType=VARCHAR},
      </if>
      <if test="pay_sn != null">
        pay_sn = #{pay_sn,jdbcType=VARCHAR},
      </if>
      <if test="is_cod != null">
        is_cod = #{is_cod,jdbcType=BIT},
      </if>
      <if test="order_amount != null">
        order_amount = #{order_amount,jdbcType=DECIMAL},
      </if>
      <if test="order_points != null">
        order_points = #{order_points,jdbcType=INTEGER},
      </if>
      <if test="money_paid != null">
        money_paid = #{money_paid,jdbcType=DECIMAL},
      </if>
      <if test="goods_amount != null">
        goods_amount = #{goods_amount,jdbcType=DECIMAL},
      </if>
      <if test="inv_fee != null">
        inv_fee = #{inv_fee,jdbcType=DECIMAL},
      </if>
      <if test="shipping_fee != null">
        shipping_fee = #{shipping_fee,jdbcType=DECIMAL},
      </if>
      <if test="cash_more != null">
        cash_more = #{cash_more,jdbcType=DECIMAL},
      </if>
      <if test="discount_fee != null">
        discount_fee = #{discount_fee,jdbcType=DECIMAL},
      </if>
      <if test="change_amount != null">
        change_amount = #{change_amount,jdbcType=DECIMAL},
      </if>
      <if test="shipping_change != null">
        shipping_change = #{shipping_change,jdbcType=DECIMAL},
      </if>
      <if test="surplus != null">
        surplus = #{surplus,jdbcType=DECIMAL},
      </if>
      <if test="user_surplus != null">
        user_surplus = #{user_surplus,jdbcType=DECIMAL},
      </if>
      <if test="user_surplus_limit != null">
        user_surplus_limit = #{user_surplus_limit,jdbcType=DECIMAL},
      </if>
      <if test="bonus_id != null">
        bonus_id = #{bonus_id,jdbcType=INTEGER},
      </if>
      <if test="shop_bonus_id != null">
        shop_bonus_id = #{shop_bonus_id,jdbcType=INTEGER},
      </if>
      <if test="bonus != null">
        bonus = #{bonus,jdbcType=DECIMAL},
      </if>
      <if test="shop_bonus != null">
        shop_bonus = #{shop_bonus,jdbcType=DECIMAL},
      </if>
      <if test="store_card_id != null">
        store_card_id = #{store_card_id,jdbcType=INTEGER},
      </if>
      <if test="store_card_price != null">
        store_card_price = #{store_card_price,jdbcType=DECIMAL},
      </if>
      <if test="integral != null">
        integral = #{integral,jdbcType=INTEGER},
      </if>
      <if test="integral_money != null">
        integral_money = #{integral_money,jdbcType=DECIMAL},
      </if>
      <if test="give_integral != null">
        give_integral = #{give_integral,jdbcType=INTEGER},
      </if>
      <if test="order_from != null">
        order_from = #{order_from,jdbcType=VARCHAR},
      </if>
      <if test="add_time != null">
        add_time = #{add_time,jdbcType=INTEGER},
      </if>
      <if test="pay_time != null">
        pay_time = #{pay_time,jdbcType=INTEGER},
      </if>
      <if test="shipping_time != null">
        shipping_time = #{shipping_time,jdbcType=INTEGER},
      </if>
      <if test="confirm_time != null">
        confirm_time = #{confirm_time,jdbcType=INTEGER},
      </if>
      <if test="delay_days != null">
        delay_days = #{delay_days,jdbcType=BIT},
      </if>
      <if test="order_type != null">
        order_type = #{order_type,jdbcType=BIT},
      </if>
      <if test="service_mark != null">
        service_mark = #{service_mark,jdbcType=BIT},
      </if>
      <if test="send_mark != null">
        send_mark = #{send_mark,jdbcType=BIT},
      </if>
      <if test="shipping_mark != null">
        shipping_mark = #{shipping_mark,jdbcType=BIT},
      </if>
      <if test="buyer_type != null">
        buyer_type = #{buyer_type,jdbcType=BIT},
      </if>
      <if test="evaluate_status != null">
        evaluate_status = #{evaluate_status,jdbcType=BIT},
      </if>
      <if test="evaluate_time != null">
        evaluate_time = #{evaluate_time,jdbcType=INTEGER},
      </if>
      <if test="end_time != null">
        end_time = #{end_time,jdbcType=INTEGER},
      </if>
      <if test="is_distrib != null">
        is_distrib = #{is_distrib,jdbcType=BIT},
      </if>
      <if test="distrib_status != null">
        distrib_status = #{distrib_status,jdbcType=BIT},
      </if>
      <if test="is_show != null">
        is_show = #{is_show,jdbcType=VARCHAR},
      </if>
      <if test="is_delete != null">
        is_delete = #{is_delete,jdbcType=BIT},
      </if>
      <if test="close_reason != null">
        close_reason = #{close_reason,jdbcType=VARCHAR},
      </if>
      <if test="cash_user_id != null">
        cash_user_id = #{cash_user_id,jdbcType=INTEGER},
      </if>
      <if test="last_time != null">
        last_time = #{last_time,jdbcType=INTEGER},
      </if>
      <if test="order_cancel != null">
        order_cancel = #{order_cancel,jdbcType=BIT},
      </if>
      <if test="refuse_reason != null">
        refuse_reason = #{refuse_reason,jdbcType=VARCHAR},
      </if>
      <if test="sub_order_id != null">
        sub_order_id = #{sub_order_id,jdbcType=INTEGER},
      </if>
      <if test="is_freebuy != null">
        is_freebuy = #{is_freebuy,jdbcType=BIT},
      </if>
      <if test="order_data != null">
        order_data = #{order_data,jdbcType=LONGVARCHAR},
      </if>
      <if test="mall_remark != null">
        mall_remark = #{mall_remark,jdbcType=LONGVARCHAR},
      </if>
      <if test="shop_remark != null">
        shop_remark = #{shop_remark,jdbcType=LONGVARCHAR},
      </if>
      <if test="store_remark != null">
        store_remark = #{store_remark,jdbcType=LONGVARCHAR},
      </if>
    </set>
    where order_id = #{order_id,jdbcType=INTEGER}
  </update>
  <update id="updateByPrimaryKeyWithBLOBs" parameterType="com.pugutang.spring.boot.entity.OrderDoWithBLOBs">
    update szy_order
    set order_sn = #{order_sn,jdbcType=VARCHAR},
      parent_sn = #{parent_sn,jdbcType=VARCHAR},
      user_id = #{user_id,jdbcType=INTEGER},
      order_status = #{order_status,jdbcType=BIT},
      shop_id = #{shop_id,jdbcType=INTEGER},
      site_id = #{site_id,jdbcType=INTEGER},
      store_id = #{store_id,jdbcType=INTEGER},
      pickup_id = #{pickup_id,jdbcType=INTEGER},
      shipping_status = #{shipping_status,jdbcType=BIT},
      pay_status = #{pay_status,jdbcType=BIT},
      consignee = #{consignee,jdbcType=VARCHAR},
      region_code = #{region_code,jdbcType=VARCHAR},
      region_name = #{region_name,jdbcType=VARCHAR},
      address = #{address,jdbcType=VARCHAR},
      address_lng = #{address_lng,jdbcType=VARCHAR},
      address_lat = #{address_lat,jdbcType=VARCHAR},
      receiving_mode = #{receiving_mode,jdbcType=BIT},
      tel = #{tel,jdbcType=VARCHAR},
      email = #{email,jdbcType=VARCHAR},
      postscript = #{postscript,jdbcType=VARCHAR},
      best_time = #{best_time,jdbcType=VARCHAR},
      pay_id = #{pay_id,jdbcType=INTEGER},
      pay_code = #{pay_code,jdbcType=VARCHAR},
      pay_name = #{pay_name,jdbcType=VARCHAR},
      pay_sn = #{pay_sn,jdbcType=VARCHAR},
      is_cod = #{is_cod,jdbcType=BIT},
      order_amount = #{order_amount,jdbcType=DECIMAL},
      order_points = #{order_points,jdbcType=INTEGER},
      money_paid = #{money_paid,jdbcType=DECIMAL},
      goods_amount = #{goods_amount,jdbcType=DECIMAL},
      inv_fee = #{inv_fee,jdbcType=DECIMAL},
      shipping_fee = #{shipping_fee,jdbcType=DECIMAL},
      cash_more = #{cash_more,jdbcType=DECIMAL},
      discount_fee = #{discount_fee,jdbcType=DECIMAL},
      change_amount = #{change_amount,jdbcType=DECIMAL},
      shipping_change = #{shipping_change,jdbcType=DECIMAL},
      surplus = #{surplus,jdbcType=DECIMAL},
      user_surplus = #{user_surplus,jdbcType=DECIMAL},
      user_surplus_limit = #{user_surplus_limit,jdbcType=DECIMAL},
      bonus_id = #{bonus_id,jdbcType=INTEGER},
      shop_bonus_id = #{shop_bonus_id,jdbcType=INTEGER},
      bonus = #{bonus,jdbcType=DECIMAL},
      shop_bonus = #{shop_bonus,jdbcType=DECIMAL},
      store_card_id = #{store_card_id,jdbcType=INTEGER},
      store_card_price = #{store_card_price,jdbcType=DECIMAL},
      integral = #{integral,jdbcType=INTEGER},
      integral_money = #{integral_money,jdbcType=DECIMAL},
      give_integral = #{give_integral,jdbcType=INTEGER},
      order_from = #{order_from,jdbcType=VARCHAR},
      add_time = #{add_time,jdbcType=INTEGER},
      pay_time = #{pay_time,jdbcType=INTEGER},
      shipping_time = #{shipping_time,jdbcType=INTEGER},
      confirm_time = #{confirm_time,jdbcType=INTEGER},
      delay_days = #{delay_days,jdbcType=BIT},
      order_type = #{order_type,jdbcType=BIT},
      service_mark = #{service_mark,jdbcType=BIT},
      send_mark = #{send_mark,jdbcType=BIT},
      shipping_mark = #{shipping_mark,jdbcType=BIT},
      buyer_type = #{buyer_type,jdbcType=BIT},
      evaluate_status = #{evaluate_status,jdbcType=BIT},
      evaluate_time = #{evaluate_time,jdbcType=INTEGER},
      end_time = #{end_time,jdbcType=INTEGER},
      is_distrib = #{is_distrib,jdbcType=BIT},
      distrib_status = #{distrib_status,jdbcType=BIT},
      is_show = #{is_show,jdbcType=VARCHAR},
      is_delete = #{is_delete,jdbcType=BIT},
      close_reason = #{close_reason,jdbcType=VARCHAR},
      cash_user_id = #{cash_user_id,jdbcType=INTEGER},
      last_time = #{last_time,jdbcType=INTEGER},
      order_cancel = #{order_cancel,jdbcType=BIT},
      refuse_reason = #{refuse_reason,jdbcType=VARCHAR},
      sub_order_id = #{sub_order_id,jdbcType=INTEGER},
      is_freebuy = #{is_freebuy,jdbcType=BIT},
      order_data = #{order_data,jdbcType=LONGVARCHAR},
      mall_remark = #{mall_remark,jdbcType=LONGVARCHAR},
      shop_remark = #{shop_remark,jdbcType=LONGVARCHAR},
      store_remark = #{store_remark,jdbcType=LONGVARCHAR}
    where order_id = #{order_id,jdbcType=INTEGER}
  </update>
  <update id="updateByPrimaryKey" parameterType="com.pugutang.spring.boot.entity.OrderDo">
    update szy_order
    set order_sn = #{order_sn,jdbcType=VARCHAR},
      parent_sn = #{parent_sn,jdbcType=VARCHAR},
      user_id = #{user_id,jdbcType=INTEGER},
      order_status = #{order_status,jdbcType=BIT},
      shop_id = #{shop_id,jdbcType=INTEGER},
      site_id = #{site_id,jdbcType=INTEGER},
      store_id = #{store_id,jdbcType=INTEGER},
      pickup_id = #{pickup_id,jdbcType=INTEGER},
      shipping_status = #{shipping_status,jdbcType=BIT},
      pay_status = #{pay_status,jdbcType=BIT},
      consignee = #{consignee,jdbcType=VARCHAR},
      region_code = #{region_code,jdbcType=VARCHAR},
      region_name = #{region_name,jdbcType=VARCHAR},
      address = #{address,jdbcType=VARCHAR},
      address_lng = #{address_lng,jdbcType=VARCHAR},
      address_lat = #{address_lat,jdbcType=VARCHAR},
      receiving_mode = #{receiving_mode,jdbcType=BIT},
      tel = #{tel,jdbcType=VARCHAR},
      email = #{email,jdbcType=VARCHAR},
      postscript = #{postscript,jdbcType=VARCHAR},
      best_time = #{best_time,jdbcType=VARCHAR},
      pay_id = #{pay_id,jdbcType=INTEGER},
      pay_code = #{pay_code,jdbcType=VARCHAR},
      pay_name = #{pay_name,jdbcType=VARCHAR},
      pay_sn = #{pay_sn,jdbcType=VARCHAR},
      is_cod = #{is_cod,jdbcType=BIT},
      order_amount = #{order_amount,jdbcType=DECIMAL},
      order_points = #{order_points,jdbcType=INTEGER},
      money_paid = #{money_paid,jdbcType=DECIMAL},
      goods_amount = #{goods_amount,jdbcType=DECIMAL},
      inv_fee = #{inv_fee,jdbcType=DECIMAL},
      shipping_fee = #{shipping_fee,jdbcType=DECIMAL},
      cash_more = #{cash_more,jdbcType=DECIMAL},
      discount_fee = #{discount_fee,jdbcType=DECIMAL},
      change_amount = #{change_amount,jdbcType=DECIMAL},
      shipping_change = #{shipping_change,jdbcType=DECIMAL},
      surplus = #{surplus,jdbcType=DECIMAL},
      user_surplus = #{user_surplus,jdbcType=DECIMAL},
      user_surplus_limit = #{user_surplus_limit,jdbcType=DECIMAL},
      bonus_id = #{bonus_id,jdbcType=INTEGER},
      shop_bonus_id = #{shop_bonus_id,jdbcType=INTEGER},
      bonus = #{bonus,jdbcType=DECIMAL},
      shop_bonus = #{shop_bonus,jdbcType=DECIMAL},
      store_card_id = #{store_card_id,jdbcType=INTEGER},
      store_card_price = #{store_card_price,jdbcType=DECIMAL},
      integral = #{integral,jdbcType=INTEGER},
      integral_money = #{integral_money,jdbcType=DECIMAL},
      give_integral = #{give_integral,jdbcType=INTEGER},
      order_from = #{order_from,jdbcType=VARCHAR},
      add_time = #{add_time,jdbcType=INTEGER},
      pay_time = #{pay_time,jdbcType=INTEGER},
      shipping_time = #{shipping_time,jdbcType=INTEGER},
      confirm_time = #{confirm_time,jdbcType=INTEGER},
      delay_days = #{delay_days,jdbcType=BIT},
      order_type = #{order_type,jdbcType=BIT},
      service_mark = #{service_mark,jdbcType=BIT},
      send_mark = #{send_mark,jdbcType=BIT},
      shipping_mark = #{shipping_mark,jdbcType=BIT},
      buyer_type = #{buyer_type,jdbcType=BIT},
      evaluate_status = #{evaluate_status,jdbcType=BIT},
      evaluate_time = #{evaluate_time,jdbcType=INTEGER},
      end_time = #{end_time,jdbcType=INTEGER},
      is_distrib = #{is_distrib,jdbcType=BIT},
      distrib_status = #{distrib_status,jdbcType=BIT},
      is_show = #{is_show,jdbcType=VARCHAR},
      is_delete = #{is_delete,jdbcType=BIT},
      close_reason = #{close_reason,jdbcType=VARCHAR},
      cash_user_id = #{cash_user_id,jdbcType=INTEGER},
      last_time = #{last_time,jdbcType=INTEGER},
      order_cancel = #{order_cancel,jdbcType=BIT},
      refuse_reason = #{refuse_reason,jdbcType=VARCHAR},
      sub_order_id = #{sub_order_id,jdbcType=INTEGER},
      is_freebuy = #{is_freebuy,jdbcType=BIT}
    where order_id = #{order_id,jdbcType=INTEGER}
  </update>
</mapper>